KakaoV2/__init__.py
KakaoV2/channel.py
KakaoV2/client.py
KakaoV2/error.py
KakaoV2/http.py
KakaoV2/message.py
KakaoV2/utils.py
KakaoV2-1.1.0.dist-info/LICENSE
KakaoV2-1.1.0.dist-info/METADATA
KakaoV2-1.1.0.dist-info/WHEEL
KakaoV2-1.1.0.dist-info/top_level.txt
KakaoV2-1.1.0.dist-info/RECORD
