Metadata-Version: 2.1
Name: KakaoV2
Version: 1.1.0
Summary: Kakaotalk LOCO/HTTP API protocol wrapper for python.
Home-page: https://github.com/ULTRA0221/KakaoV2
Author: ULTRA#0221
Author-email: kakao@ultra0221.me
License: UNKNOWN
Platform: UNKNOWN
Classifier: License :: OSI Approved :: MIT License
License-File: LICENSE
Requires-Dist: pymongo
Requires-Dist: requests
Requires-Dist: pycryptodomex
Requires-Dist: aiohttp
